topsis/___init__.py
topsis/__main__.py
Topsis_Saksham_102003039-1.0.0.dist-info/LICENSE
Topsis_Saksham_102003039-1.0.0.dist-info/METADATA
Topsis_Saksham_102003039-1.0.0.dist-info/WHEEL
Topsis_Saksham_102003039-1.0.0.dist-info/entry_points.txt
Topsis_Saksham_102003039-1.0.0.dist-info/top_level.txt
Topsis_Saksham_102003039-1.0.0.dist-info/RECORD
