Metadata-Version: 2.1
Name: Topsis-Saksham-102003039
Version: 1.0.0
Summary: Topsis package for Multiple Criteria Decision Making problems(MCDM) problems
Home-page: https://github.com/SakshamKhetarpal/Topsis.git
Author: Saksham Khetarpal
Author-email: sakshamkhetarpal@gmail.com
License: MIT
Classifier: License :: OSI Approved :: MIT License
Classifier: Programming Language :: Python :: 3.6
Classifier: Programming Language :: Python :: 3.7
Classifier: Programming Language :: Python :: 3.8
Classifier: Programming Language :: Python :: 3.9
Classifier: Programming Language :: Python :: 3.10
Classifier: Programming Language :: Python :: 3.11
Classifier: Operating System :: OS Independent
Requires-Python: >=3.6
License-File: LICENSE
Requires-Dist: pandas
Requires-Dist: numpy
